wsba_hockey/__init__.py
wsba_hockey/wsba_main.py
wsba_hockey/tools/__init__.py
wsba_hockey/tools/agg.py
wsba_hockey/tools/columns.py
wsba_hockey/tools/game_score.py
wsba_hockey/tools/plotting.py
wsba_hockey/tools/scraping.py
wsba_hockey/tools/xg_model.py
wsba_hockey/tools/archive/old_scraping.py
wsba_hockey/tools/utils/__init__.py
wsba_hockey/tools/utils/shared.py
wsba_hockey-1.4.1.dist-info/licenses/LICENSE
wsba_hockey-1.4.1.dist-info/METADATA
wsba_hockey-1.4.1.dist-info/WHEEL
wsba_hockey-1.4.1.dist-info/top_level.txt
wsba_hockey-1.4.1.dist-info/RECORD
