Metadata-Version: 2.4
Name: wsba_hockey
Version: 1.4.1
Summary: WeakSide Breakout's complete Python package of access to hockey data, primairly including the scraping of National Hockey League schedule, play-by-play, and shifts information.
Author-email: Owen Singh <owenbksingh@gmail.com>
Project-URL: Homepage, https://github.com/owensingh38/wsba_hockey/
Keywords: wsba,hockey,scraping,NHL,analytics
Classifier: Programming Language :: Python :: 3
Classifier: License :: OSI Approved :: MIT License
Classifier: Operating System :: OS Independent
Requires-Python: >=3.8
License-File: LICENSE
Dynamic: license-file
